mobilus_client/__init__.py
mobilus_client/__main__.py
mobilus_client/app.py
mobilus_client/client.py
mobilus_client/config.py
mobilus_client/py.typed
mobilus_client/messages/__init__.py
mobilus_client/messages/encryptor.py
mobilus_client/messages/factory.py
mobilus_client/messages/serializer.py
mobilus_client/messages/status.py
mobilus_client/messages/validator.py
mobilus_client/proto/__init__.py
mobilus_client/proto/call_events_request.proto
mobilus_client/proto/call_events_request_pb2.py
mobilus_client/proto/call_events_request_pb2.pyi
mobilus_client/proto/current_state_request.proto
mobilus_client/proto/current_state_request_pb2.py
mobilus_client/proto/current_state_request_pb2.pyi
mobilus_client/proto/current_state_response.proto
mobilus_client/proto/current_state_response_pb2.py
mobilus_client/proto/current_state_response_pb2.pyi
mobilus_client/proto/devices_list_request.proto
mobilus_client/proto/devices_list_request_pb2.py
mobilus_client/proto/devices_list_request_pb2.pyi
mobilus_client/proto/devices_list_response.proto
mobilus_client/proto/devices_list_response_pb2.py
mobilus_client/proto/devices_list_response_pb2.pyi
mobilus_client/proto/login_request.proto
mobilus_client/proto/login_request_pb2.py
mobilus_client/proto/login_request_pb2.pyi
mobilus_client/proto/login_response.proto
mobilus_client/proto/login_response_pb2.py
mobilus_client/proto/login_response_pb2.pyi
mobilus_client/registries/__init__.py
mobilus_client/registries/key.py
mobilus_client/registries/message.py
mobilus_client/utils/__init__.py
mobilus_client/utils/encryption.py
mobilus_client/utils/types.py
mobilus_client-0.2.0.dist-info/METADATA
mobilus_client-0.2.0.dist-info/WHEEL
mobilus_client-0.2.0.dist-info/licenses/LICENSE
mobilus_client-0.2.0.dist-info/RECORD
