Metadata-Version: 2.4
Name: mobilus-client
Version: 0.2.0
Summary: Python client for Mobilus Cosmo GTW
Project-URL: homepage, https://github.com/zpieslak/mobilus-client
Project-URL: issues, https://github.com/zpieslak/mobilus-client/issues
Author-email: Zbigniew Pieślak <zpieslak@gmail.com>
License: MIT License
License-File: LICENSE
Classifier: License :: OSI Approved :: MIT License
Classifier: Operating System :: OS Independent
Classifier: Programming Language :: Python :: 3
Requires-Python: >=3.9
Requires-Dist: cryptography>=35.0
Requires-Dist: paho-mqtt~=2.1.0
Requires-Dist: protobuf>=3.20
Provides-Extra: test
Requires-Dist: coverage>=7.0; extra == 'test'
Requires-Dist: factory-boy==3.3.1; extra == 'test'
Requires-Dist: mypy-protobuf>=3.0; extra == 'test'
Requires-Dist: mypy>=1.0; extra == 'test'
Requires-Dist: ruff>=0.9.0; extra == 'test'
Requires-Dist: types-protobuf>=3.20; extra == 'test'
